Workbook

Sheet Panel_Cost_Table
I1: RAW MATERIALS
A2: NO | B2: Full Coding | C2: Panel Type | D2: Tank Height(mH) | E2: SIZE | I2: SMC | J2: 5 | K2: G/C | L2: =1050/1050/180 -> 0.0055555556 | M2: Raw Material Sum | N2: PRESSING TIME | O2: C/TIME | P2: Molding Processing Cost | X2: Drilling Processing Cost | AE2: Processing Cost Sum | AF2: Insulation Cost | AJ2: Insulation Cost Sum | AK2: Cost Work in Progress | AN2: Manufacturing Cost | AP2: 제조원가
C3: Name | E3: W | F3: L | G3: Flange_H | H3: T_H | I3: WT(KG) | J3: PRICE | K3: G/C(g) | L3: PkG MAT | P3: Press Machine | Q3: Equipment Cost/Hr | R3: Prodcution Q'ty/Hr | S3: Equipment Cost/each Product | T3: No. of Labors | U3: Labor Cost/Hr | V3: Labor Cost/each Product | W3: Total Processing Cost | X3: Equipment Cost/Hr | Y3: Prodcution Q'ty/Hr | Z3: Equipment Cost/each Product | AA3: No. of Labors | AB3: Labor Cost/Hr | AC3: Labor Cost/each Product | AD3: Total Processing Cost | AF3: Raw Material (Insulation Skin) | AG3: Raw Material (MDI) | AH3: Raw Material (POLYOL) | AI3: Processing | AK3: After Molding | AL3: After Drilling | AM3: After Insulation | AN3: Non-Insulated Panel | AO3: Insulated Panel | AP3: 단 판 | AQ3: 보 온
A4: 1 | B4: MF00 | C4: Manhole(1m x 1m) | D4: 000 | E4: 1000 | F4: 1000 | G4: 55 | I4: =4.2+10 -> 14.2 | J4: =I4*$J$2 -> 71 | M4: =J4+L4 -> 71 | N4: 240 | O4: 300 | P4: 1200 TON | Q4: ='Equipment Costs(Press_Machine)'!$F$43 -> 34.596964 | R4: =3600/O4 -> 12 | S4: =Q4/R4 -> 2.8830803 | T4: 2 | U4: =LABOUR_Cost!$B$17 -> 7.2154472 | V4: =T4*U4/R4 -> 1.2025745 | W4: =S4+V4 -> 4.0856549 | X4: ='Equipment Costs(Drilling)'!$F$39 -> 7.8894021 | Y4: 30 | Z4: =X4/Y4 -> 0.26298007 | AA4: 2 | AB4: =LABOUR_Cost!$B$17 -> 7.2154472 | AC4: =AA4*AB4/Y4 -> 0.48102981 | AD4: =Z4+AC4 -> 0.74400988 | AE4: =M4+W4+AD4 -> 75.829665
A5: 2 | B5: RF00 | C5: Roof(1x1M) | D5: 000 | E5: 1000 | F5: 1000 | G5: 55 | H5: 160 | I5: 8.5 | J5: =I5*$J$2 -> 42.5 | M5: =J5+L5 -> 42.5 | N5: 240 | O5: =N5+100 -> 340 | P5: 800TON | Q5: ='Equipment Costs(Press_Machine)'!$F$43 -> 34.596964 | R5: =3600/O5 -> 10.588235 | S5: =Q5/R5 -> 3.267491 | T5: 2 | U5: =LABOUR_Cost!$B$17 -> 7.2154472 | V5: =T5*U5/R5 -> 1.3629178 | W5: =S5+V5 -> 4.6304088 | X5: ='Equipment Costs(Drilling)'!$F$39 -> 7.8894021 | Y5: 30 | Z5: =X5/Y5 -> 0.26298007 | AA5: 2 | AB5: =LABOUR_Cost!$B$17 -> 7.2154472 | AC5: =AA5*AB5/Y5 -> 0.48102981 | AD5: =Z5+AC5 -> 0.74400988 | AE5: =M5+W5+AD5 -> 47.874419
A6: 3 | B6: BF10 | C6: Base(1x1M) | D6: 100 | E6: 1000 | F6: 1000 | G6: =69.5-3 -> 66.5 | H6: =200-2 -> 198 | I6: =19.9-3*1.8 -> 14.5 | J6: =I6*$J$2 -> 72.5 | K6: =1.15*1.15*180 -> 238.05 | L6: =K6*$L$2 -> 1.3225 | M6: =J6+L6 -> 73.8225 | N6: 300 | O6: =N6+100 -> 400 | P6: 800 TON | Q6: ='Equipment Costs(Press_Machine)'!$F$43 -> 34.596964 | R6: =3600/O6 -> 9 | S6: =Q6/R6 -> 3.8441071 | T6: 2 | U6: =LABOUR_Cost!$B$17 -> 7.2154472 | V6: =T6*U6/R6 -> 1.6034327 | W6: =S6+V6 -> 5.4475398 | X6: ='Equipment Costs(Drilling)'!$F$39 -> 7.8894021 | Y6: 30 | Z6: =X6/Y6 -> 0.26298007 | AA6: 2 | AB6: =LABOUR_Cost!$B$17 -> 7.2154472 | AC6: =AA6*AB6/Y6 -> 0.48102981 | AD6: =Z6+AC6 -> 0.74400988 | AE6: =M6+W6+AD6 -> 80.01405
A7: 4 | B7: BF20 | C7: Base(1x1M) | D7: 200 | E7: 1000 | F7: 1000 | G7: =69.5-2 -> 67.5 | H7: =200-2 -> 198 | I7: 16 | J7: =I7*$J$2 -> 80 | K7: =1.15*1.15*180 -> 238.05 | L7: =K7*$L$2 -> 1.3225 | M7: =J7+L7 -> 81.3225 | N7: 300 | O7: =N7+100 -> 400 | P7: 800 TON | Q7: ='Equipment Costs(Press_Machine)'!$F$43 -> 34.596964 | R7: =3600/O7 -> 9 | S7: =Q7/R7 -> 3.8441071 | T7: 2 | U7: =LABOUR_Cost!$B$17 -> 7.2154472 | V7: =T7*U7/R7 -> 1.6034327 | W7: =S7+V7 -> 5.4475398 | X7: ='Equipment Costs(Drilling)'!$F$39 -> 7.8894021 | Y7: 30 | Z7: =X7/Y7 -> 0.26298007 | AA7: 2 | AB7: =LABOUR_Cost!$B$17 -> 7.2154472 | AC7: =AA7*AB7/Y7 -> 0.48102981 | AD7: =Z7+AC7 -> 0.74400988 | AE7: =M7+W7+AD7 -> 87.51405
A8: 5 | B8: BF30 | C8: Base(1x1M) | D8: 300 | E8: 1000 | F8: 1000 | G8: 69.5 | H8: =200-2 -> 198 | I8: 21 | J8: =I8*$J$2 -> 105 | K8: =1.15*1.15*180 -> 238.05 | L8: =K8*$L$2 -> 1.3225 | M8: =J8+L8 -> 106.3225 | N8: 360 | O8: =N8+100 -> 460 | P8: 800 TON | Q8: ='Equipment Costs(Press_Machine)'!$F$43 -> 34.596964 | R8: =3600/O8 -> 7.826087 | S8: =Q8/R8 -> 4.4207232 | T8: 2 | U8: =LABOUR_Cost!$B$17 -> 7.2154472 | V8: =T8*U8/R8 -> 1.8439476 | W8: =S8+V8 -> 6.2646708 | X8: ='Equipment Costs(Drilling)'!$F$39 -> 7.8894021 | Y8: 30 | Z8: =X8/Y8 -> 0.26298007 | AA8: 2 | AB8: =LABOUR_Cost!$B$17 -> 7.2154472 | AC8: =AA8*AB8/Y8 -> 0.48102981 | AD8: =Z8+AC8 -> 0.74400988 | AE8: =M8+W8+AD8 -> 113.33118
A9: 6 | B9: BF40 | C9: Base(1x1M) | D9: 400 | E9: 1000 | F9: 1000 | G9: =69.5+1.5 -> 71 | H9: =200-2 -> 198 | I9: 23.5 | J9: =I9*$J$2 -> 117.5 | K9: =1.15*1.15*180 -> 238.05 | L9: =K9*$L$2 -> 1.3225 | M9: =J9+L9 -> 118.8225 | N9: 360 | O9: =N9+100 -> 460 | P9: 800 TON | Q9: ='Equipment Costs(Press_Machine)'!$F$43 -> 34.596964 | R9: =3600/O9 -> 7.826087 | S9: =Q9/R9 -> 4.4207232 | T9: 2 | U9: =LABOUR_Cost!$B$17 -> 7.2154472 | V9: =T9*U9/R9 -> 1.8439476 | W9: =S9+V9 -> 6.2646708 | X9: ='Equipment Costs(Drilling)'!$F$39 -> 7.8894021 | Y9: 30 | Z9: =X9/Y9 -> 0.26298007 | AA9: 2 | AB9: =LABOUR_Cost!$B$17 -> 7.2154472 | AC9: =AA9*AB9/Y9 -> 0.48102981 | AD9: =Z9+AC9 -> 0.74400988 | AE9: =M9+W9+AD9 -> 125.83118
A10: 7 | B10: NH15 | C10: FLAT HALF(0.5x1M) | D10: 150 | E10: 500 | F10: 1000 | G10: 69 | H10: 69 | I10: 7.2 | J10: =I10*$J$2 -> 36 | K10: =1.15*1.15*180 -> 238.05 | L10: =K10*$L$2 -> 1.3225 | M10: =J10+L10 -> 37.3225 | N10: 420 | O10: =N10+100 -> 520 | P10: 800 TON | Q10: ='Equipment Costs(Press_Machine)'!$F$43 -> 34.596964 | R10: =3600/O10 -> 6.9230769 | S10: =Q10/R10 -> 4.9973392 | T10: 1 | U10: =LABOUR_Cost!$B$17 -> 7.2154472 | V10: =T10*U10/R10 -> 1.0422313 | W10: =S10+V10 -> 6.0395705 | X10: ='Equipment Costs(Drilling)'!$F$39 -> 7.8894021 | Y10: 30 | Z10: =X10/Y10 -> 0.26298007 | AA10: 1 | AB10: =LABOUR_Cost!$B$17 -> 7.2154472 | AC10: =AA10*AB10/Y10 -> 0.24051491 | AD10: =Z10+AC10 -> 0.50349497 | AE10: =M10+W10+AD10 -> 43.865565
A11: 8 | B11: NH25 | C11: FLAT HALF(0.5x1M) | D11: 250 | E11: 500 | F11: 1000 | G11: 70 | H11: 70 | I11: 8.7 | J11: =I11*$J$2 -> 43.5 | K11: =1.15*1.15*180 -> 238.05 | L11: =K11*$L$2 -> 1.3225 | M11: =J11+L11 -> 44.8225 | N11: =60*6+30 -> 390 | O11: =N11+100 -> 490 | P11: 800 TON | Q11: ='Equipment Costs(Press_Machine)'!$F$43 -> 34.596964 | R11: =3600/O11 -> 7.3469388 | S11: =Q11/R11 -> 4.7090312 | T11: 1 | U11: =LABOUR_Cost!$B$17 -> 7.2154472 | V11: =T11*U11/R11 -> 0.98210253 | W11: =S11+V11 -> 5.6911337 | X11: ='Equipment Costs(Drilling)'!$F$39 -> 7.8894021 | Y11: 30 | Z11: =X11/Y11 -> 0.26298007 | AA11: 1 | AB11: =LABOUR_Cost!$B$17 -> 7.2154472 | AC11: =AA11*AB11/Y11 -> 0.24051491 | AD11: =Z11+AC11 -> 0.50349497 | AE11: =M11+W11+AD11 -> 51.017129
A12: 9 | B12: NH35 | C12: FLAT HALF(0.5x1M) | D12: 350 | E12: 500 | F12: 1000 | G12: 72 | H12: 72 | I12: 11.4 | J12: =I12*$J$2 -> 57 | K12: =1.15*1.15*180 -> 238.05 | L12: =K12*$L$2 -> 1.3225 | M12: =J12+L12 -> 58.3225 | N12: =60*9+30 -> 570 | O12: =N12+100 -> 670 | P12: 800 TON | Q12: ='Equipment Costs(Press_Machine)'!$F$43 -> 34.596964 | R12: =3600/O12 -> 5.3731343 | S12: =Q12/R12 -> 6.4388794 | T12: 1 | U12: =LABOUR_Cost!$B$17 -> 7.2154472 | V12: =T12*U12/R12 -> 1.3428749 | W12: =S12+V12 -> 7.7817543 | X12: ='Equipment Costs(Drilling)'!$F$39 -> 7.8894021 | Y12: 30 | Z12: =X12/Y12 -> 0.26298007 | AA12: 1 | AB12: =LABOUR_Cost!$B$17 -> 7.2154472 | AC12: =AA12*AB12/Y12 -> 0.24051491 | AD12: =Z12+AC12 -> 0.50349497 | AE12: =M12+W12+AD12 -> 66.607749
A13: 10 | B13: NH40 | C13: FLAT HALF(0.5x1M) | D13: 400 | E13: 500 | F13: 1000 | G13: 72 | H13: 72 | I13: 13.5 | J13: =I13*$J$2 -> 67.5 | K13: =1.15*1.15*180 -> 238.05 | L13: =K13*$L$2 -> 1.3225 | M13: =J13+L13 -> 68.8225 | N13: =60*9+30 -> 570 | O13: =N13+100 -> 670 | P13: 800 TON | Q13: ='Equipment Costs(Press_Machine)'!$F$43 -> 34.596964 | R13: =3600/O13 -> 5.3731343 | S13: =Q13/R13 -> 6.4388794 | T13: 1 | U13: =LABOUR_Cost!$B$17 -> 7.2154472 | V13: =T13*U13/R13 -> 1.3428749 | W13: =S13+V13 -> 7.7817543 | X13: ='Equipment Costs(Drilling)'!$F$39 -> 7.8894021 | Y13: 30 | Z13: =X13/Y13 -> 0.26298007 | AA13: 1 | AB13: =LABOUR_Cost!$B$17 -> 7.2154472 | AC13: =AA13*AB13/Y13 -> 0.24051491 | AD13: =Z13+AC13 -> 0.50349497 | AE13: =M13+W13+AD13 -> 77.107749
A14: 11 | B14: NF10 | C14: Nozzle_Drain(1x1m) | D14: 100 | E14: 1000 | F14: 1000 | G14: 68.5 | H14: 68.5 | I14: 12.5 | J14: =I14*$J$2 -> 62.5 | K14: =1.15*1.15*180 -> 238.05 | L14: =K14*$L$2 -> 1.3225 | M14: =J14+L14 -> 63.8225 | N14: 300 | O14: =N14+100 -> 400 | P14: 800 TON | Q14: ='Equipment Costs(Press_Machine)'!$F$43 -> 34.596964 | R14: =3600/O14 -> 9 | S14: =Q14/R14 -> 3.8441071 | T14: 2 | U14: =LABOUR_Cost!$B$17 -> 7.2154472 | V14: =T14*U14/R14 -> 1.6034327 | W14: =S14+V14 -> 5.4475398 | X14: ='Equipment Costs(Drilling)'!$F$39 -> 7.8894021 | Y14: 30 | Z14: =X14/Y14 -> 0.26298007 | AA14: 2 | AB14: =LABOUR_Cost!$B$17 -> 7.2154472 | AC14: =AA14*AB14/Y14 -> 0.48102981 | AD14: =Z14+AC14 -> 0.74400988 | AE14: =M14+W14+AD14 -> 70.01405
A15: 12 | B15: NF20 | C15: Nozzle_Drain(1x1m) | D15: 200 | E15: 1000 | F15: 1000 | G15: =68.5+3 -> 71.5 | H15: =68.5+3 -> 71.5 | I15: 17.5 | J15: =I15*$J$2 -> 87.5 | K15: =1.15*1.15*180 -> 238.05 | L15: =K15*$L$2 -> 1.3225 | M15: =J15+L15 -> 88.8225 | N15: 360 | O15: =N15+100 -> 460 | P15: 800 TON | Q15: ='Equipment Costs(Press_Machine)'!$F$43 -> 34.596964 | R15: =3600/O15 -> 7.826087 | S15: =Q15/R15 -> 4.4207232 | T15: 2 | U15: =LABOUR_Cost!$B$17 -> 7.2154472 | V15: =T15*U15/R15 -> 1.8439476 | W15: =S15+V15 -> 6.2646708 | X15: ='Equipment Costs(Drilling)'!$F$39 -> 7.8894021 | Y15: 30 | Z15: =X15/Y15 -> 0.26298007 | AA15: 2 | AB15: =LABOUR_Cost!$B$17 -> 7.2154472 | AC15: =AA15*AB15/Y15 -> 0.48102981 | AD15: =Z15+AC15 -> 0.74400988 | AE15: =M15+W15+AD15 -> 95.831181
A16: 13 | B16: NF30 | C16: Nozzle_Drain(1x1m) | D16: 300 | E16: 1000 | F16: 1000 | G16: =68.5+6.5 -> 75 | H16: =68.5+6.5 -> 75 | I16: 21 | J16: =I16*$J$2 -> 105 | K16: =1.15*1.15*180 -> 238.05 | L16: =K16*$L$2 -> 1.3225 | M16: =J16+L16 -> 106.3225 | N16: 360 | O16: =N16+100 -> 460 | P16: 800 TON | Q16: ='Equipment Costs(Press_Machine)'!$F$43 -> 34.596964 | R16: =3600/O16 -> 7.826087 | S16: =Q16/R16 -> 4.4207232 | T16: 2 | U16: =LABOUR_Cost!$B$17 -> 7.2154472 | V16: =T16*U16/R16 -> 1.8439476 | W16: =S16+V16 -> 6.2646708 | X16: ='Equipment Costs(Drilling)'!$F$39 -> 7.8894021 | Y16: 30 | Z16: =X16/Y16 -> 0.26298007 | AA16: 2 | AB16: =LABOUR_Cost!$B$17 -> 7.2154472 | AC16: =AA16*AB16/Y16 -> 0.48102981 | AD16: =Z16+AC16 -> 0.74400988 | AE16: =M16+W16+AD16 -> 113.33118
A17: 14 | B17: NF40 | C17: Nozzle_Drain(1x1m) | D17: 400 | E17: 1000 | F17: 1000 | G17: =68.5+7.5 -> 76 | H17: =68.5+7.5 -> 76 | I17: 25 | J17: =I17*$J$2 -> 125 | K17: =1.15*1.15*180 -> 238.05 | L17: =K17*$L$2 -> 1.3225 | M17: =J17+L17 -> 126.3225 | N17: 420 | O17: =N17+100 -> 520 | P17: 800 TON | Q17: ='Equipment Costs(Press_Machine)'!$F$43 -> 34.596964 | R17: =3600/O17 -> 6.9230769 | S17: =Q17/R17 -> 4.9973392 | T17: 2 | U17: =LABOUR_Cost!$B$17 -> 7.2154472 | V17: =T17*U17/R17 -> 2.0844625 | W17: =S17+V17 -> 7.0818017 | X17: ='Equipment Costs(Drilling)'!$F$39 -> 7.8894021 | Y17: 30 | Z17: =X17/Y17 -> 0.26298007 | AA17: 2 | AB17: =LABOUR_Cost!$B$17 -> 7.2154472 | AC17: =AA17*AB17/Y17 -> 0.48102981 | AD17: =Z17+AC17 -> 0.74400988 | AE17: =M17+W17+AD17 -> 134.14831
A18: 15 | B18: SF10 | C18: Side(1m x 1m) | D18: 100 | E18: 1000 | F18: 1000 | G18: 70 | H18: 70 | I18: 13.8 | J18: =I18*$J$2 -> 69 | K18: =1.15*1.15*180 -> 238.05 | L18: =K18*$L$2 -> 1.3225 | M18: =J18+L18 -> 70.3225 | N18: 300 | O18: =N18+100 -> 400 | P18: 800 TON | Q18: ='Equipment Costs(Press_Machine)'!$F$43 -> 34.596964 | R18: =3600/O18 -> 9 | S18: =Q18/R18 -> 3.8441071 | T18: 2 | U18: =LABOUR_Cost!$B$17 -> 7.2154472 | V18: =T18*U18/R18 -> 1.6034327 | W18: =S18+V18 -> 5.4475398 | X18: ='Equipment Costs(Drilling)'!$F$39 -> 7.8894021 | Y18: 30 | Z18: =X18/Y18 -> 0.26298007 | AA18: 2 | AB18: =LABOUR_Cost!$B$17 -> 7.2154472 | AC18: =AA18*AB18/Y18 -> 0.48102981 | AD18: =Z18+AC18 -> 0.74400988 | AE18: =M18+W18+AD18 -> 76.51405
A19: 16 | B19: SF20 | C19: Side(1m x 1m) | D19: 200 | E19: 1000 | F19: 1000 | G19: 72 | H19: 72 | I19: 17 | J19: =I19*$J$2 -> 85 | K19: =1.15*1.15*180 -> 238.05 | L19: =K19*$L$2 -> 1.3225 | M19: =J19+L19 -> 86.3225 | N19: 360 | O19: =N19+100 -> 460 | P19: 800 TON | Q19: ='Equipment Costs(Press_Machine)'!$F$43 -> 34.596964 | R19: =3600/O19 -> 7.826087 | S19: =Q19/R19 -> 4.4207232 | T19: 2 | U19: =LABOUR_Cost!$B$17 -> 7.2154472 | V19: =T19*U19/R19 -> 1.8439476 | W19: =S19+V19 -> 6.2646708 | X19: ='Equipment Costs(Drilling)'!$F$39 -> 7.8894021 | Y19: 30 | Z19: =X19/Y19 -> 0.26298007 | AA19: 2 | AB19: =LABOUR_Cost!$B$17 -> 7.2154472 | AC19: =AA19*AB19/Y19 -> 0.48102981 | AD19: =Z19+AC19 -> 0.74400988 | AE19: =M19+W19+AD19 -> 93.331181
A20: 17 | B20: SF30 | C20: Side(1m x 1m) | D20: 300 | E20: 1000 | F20: 1000 | G20: 74 | H20: 74 | I20: 21 | J20: =I20*$J$2 -> 105 | K20: =1.15*1.15*180 -> 238.05 | L20: =K20*$L$2 -> 1.3225 | M20: =J20+L20 -> 106.3225 | N20: 360 | O20: =N20+100 -> 460 | P20: 800 TON | Q20: ='Equipment Costs(Press_Machine)'!$F$43 -> 34.596964 | R20: =3600/O20 -> 7.826087 | S20: =Q20/R20 -> 4.4207232 | T20: 2 | U20: =LABOUR_Cost!$B$17 -> 7.2154472 | V20: =T20*U20/R20 -> 1.8439476 | W20: =S20+V20 -> 6.2646708 | X20: ='Equipment Costs(Drilling)'!$F$39 -> 7.8894021 | Y20: 30 | Z20: =X20/Y20 -> 0.26298007 | AA20: 2 | AB20: =LABOUR_Cost!$B$17 -> 7.2154472 | AC20: =AA20*AB20/Y20 -> 0.48102981 | AD20: =Z20+AC20 -> 0.74400988 | AE20: =M20+W20+AD20 -> 113.33118
A21: 18 | B21: SF40 | C21: Side(1m x 1m) | D21: 400 | E21: 1000 | F21: 1000 | G21: 77 | H21: 77 | I21: 26.5 | J21: =I21*$J$2 -> 132.5 | K21: =1.15*1.15*180 -> 238.05 | L21: =K21*$L$2 -> 1.3225 | M21: =J21+L21 -> 133.8225 | N21: 420 | O21: =N21+100 -> 520 | P21: 800 TON | Q21: ='Equipment Costs(Press_Machine)'!$F$43 -> 34.596964 | R21: =3600/O21 -> 6.9230769 | S21: =Q21/R21 -> 4.9973392 | T21: 2 | U21: =LABOUR_Cost!$B$17 -> 7.2154472 | V21: =T21*U21/R21 -> 2.0844625 | W21: =S21+V21 -> 7.0818017 | X21: ='Equipment Costs(Drilling)'!$F$39 -> 7.8894021 | Y21: 30 | Z21: =X21/Y21 -> 0.26298007 | AA21: 2 | AB21: =LABOUR_Cost!$B$17 -> 7.2154472 | AC21: =AA21*AB21/Y21 -> 0.48102981 | AD21: =Z21+AC21 -> 0.74400988 | AE21: =M21+W21+AD21 -> 141.64831
A22: 19 | B22: PF10 | C22: Partition(0.93x1.0m) | D22: 100 | E22: 930 | F22: 1000 | G22: 68.5 | H22: 68.5 | I22: =ROUNDUP(10.9+1.8*0.93*1,1) -> 12.6 | J22: =I22*$J$2 -> 63 | K22: =1.15*1.15*180 -> 238.05 | L22: =K22*$L$2 -> 1.3225 | M22: =J22+L22 -> 64.3225 | N22: =60*5+30 -> 330 | O22: =N22+100 -> 430 | P22: 800 TON | Q22: ='Equipment Costs(Press_Machine)'!$F$43 -> 34.596964 | R22: =3600/O22 -> 8.372093 | S22: =Q22/R22 -> 4.1324151 | T22: 2 | U22: =LABOUR_Cost!$B$17 -> 7.2154472 | V22: =T22*U22/R22 -> 1.7236902 | W22: =S22+V22 -> 5.8561053 | X22: ='Equipment Costs(Drilling)'!$F$39 -> 7.8894021 | Y22: 30 | Z22: =X22/Y22 -> 0.26298007 | AA22: 2 | AB22: =LABOUR_Cost!$B$17 -> 7.2154472 | AC22: =AA22*AB22/Y22 -> 0.48102981 | AD22: =Z22+AC22 -> 0.74400988 | AE22: =M22+W22+AD22 -> 70.922615
A23: 20 | B23: PF20 | C23: Partition(0.93x1.0m) | D23: 200 | E23: 930 | F23: 1000 | G23: =68.5+2.5 -> 71 | H23: =68.5+2.5 -> 71 | I23: =ROUNDUP(10.9+1.8*0.93*1*2.5,1) -> 15.1 | J23: =I23*$J$2 -> 75.5 | K23: =1.15*1.15*180 -> 238.05 | L23: =K23*$L$2 -> 1.3225 | M23: =J23+L23 -> 76.8225 | N23: =60*6+30 -> 390 | O23: =N23+100 -> 490 | P23: 800 TON | Q23: ='Equipment Costs(Press_Machine)'!$F$43 -> 34.596964 | R23: =3600/O23 -> 7.3469388 | S23: =Q23/R23 -> 4.7090312 | T23: 2 | U23: =LABOUR_Cost!$B$17 -> 7.2154472 | V23: =T23*U23/R23 -> 1.9642051 | W23: =S23+V23 -> 6.6732363 | X23: ='Equipment Costs(Drilling)'!$F$39 -> 7.8894021 | Y23: 30 | Z23: =X23/Y23 -> 0.26298007 | AA23: 2 | AB23: =LABOUR_Cost!$B$17 -> 7.2154472 | AC23: =AA23*AB23/Y23 -> 0.48102981 | AD23: =Z23+AC23 -> 0.74400988 | AE23: =M23+W23+AD23 -> 84.239746
A24: 21 | B24: PF30 | C24: Partition(0.93x1.0m) | D24: 300 | E24: 930 | F24: 1000 | G24: =68.5+5.5 -> 74 | H24: =68.5+5.5 -> 74 | I24: =ROUNDUP(10.9+1.8*0.93*1*4.5,1) -> 18.5 | J24: =I24*$J$2 -> 92.5 | K24: =1.15*1.15*180 -> 238.05 | L24: =K24*$L$2 -> 1.3225 | M24: =J24+L24 -> 93.8225 | N24: =60*6+30 -> 390 | O24: =N24+100 -> 490 | P24: 800 TON | Q24: ='Equipment Costs(Press_Machine)'!$F$43 -> 34.596964 | R24: =3600/O24 -> 7.3469388 | S24: =Q24/R24 -> 4.7090312 | T24: 2 | U24: =LABOUR_Cost!$B$17 -> 7.2154472 | V24: =T24*U24/R24 -> 1.9642051 | W24: =S24+V24 -> 6.6732363 | X24: ='Equipment Costs(Drilling)'!$F$39 -> 7.8894021 | Y24: 30 | Z24: =X24/Y24 -> 0.26298007 | AA24: 2 | AB24: =LABOUR_Cost!$B$17 -> 7.2154472 | AC24: =AA24*AB24/Y24 -> 0.48102981 | AD24: =Z24+AC24 -> 0.74400988 | AE24: =M24+W24+AD24 -> 101.23975
A25: 22 | B25: PF40 | C25: Partition(0.93x1.0m) | D25: 400 | E25: 930 | F25: 1000 | G25: =68.5+7.5 -> 76 | H25: =68.5+7.5 -> 76 | I25: =ROUNDUP(10.9+1.8*0.93*1*6,1) -> 21 | J25: =I25*$J$2 -> 105 | K25: =1.15*1.15*180 -> 238.05 | L25: =K25*$L$2 -> 1.3225 | M25: =J25+L25 -> 106.3225 | N25: =60*9+30 -> 570 | O25: =N25+100 -> 670 | P25: 800 TON | Q25: ='Equipment Costs(Press_Machine)'!$F$43 -> 34.596964 | R25: =3600/O25 -> 5.3731343 | S25: =Q25/R25 -> 6.4388794 | T25: 2 | U25: =LABOUR_Cost!$B$17 -> 7.2154472 | V25: =T25*U25/R25 -> 2.6857498 | W25: =S25+V25 -> 9.1246292 | X25: ='Equipment Costs(Drilling)'!$F$39 -> 7.8894021 | Y25: 30 | Z25: =X25/Y25 -> 0.26298007 | AA25: 2 | AB25: =LABOUR_Cost!$B$17 -> 7.2154472 | AC25: =AA25*AB25/Y25 -> 0.48102981 | AD25: =Z25+AC25 -> 0.74400988 | AE25: =M25+W25+AD25 -> 116.19114
A26: 23 | B26: SL15 | C26: Side(1m x 1.5m) | D26: 150 | E26: 1000 | F26: 1500 | G26: 70 | H26: 70 | I26: 19.3 | J26: =I26*$J$2 -> 96.5 | K26: =1.15*1.65*180 -> 341.55 | L26: =K26*$L$2 -> 1.8975 | M26: =J26+L26 -> 98.3975 | N26: 300 | O26: =N26+100 -> 400 | P26: 1200 TON | Q26: ='Equipment Costs(Press_Machine)'!$F$43 -> 34.596964 | R26: =3600/O26 -> 9 | S26: =Q26/R26 -> 3.8441071 | T26: 2 | U26: =LABOUR_Cost!$B$17 -> 7.2154472 | V26: =T26*U26/R26 -> 1.6034327 | W26: =S26+V26 -> 5.4475398 | X26: ='Equipment Costs(Drilling)'!$F$39 -> 7.8894021 | Y26: 30 | Z26: =X26/Y26 -> 0.26298007 | AA26: 2 | AB26: =LABOUR_Cost!$B$17 -> 7.2154472 | AC26: =AA26*AB26/Y26 -> 0.48102981 | AD26: =Z26+AC26 -> 0.74400988 | AE26: =M26+W26+AD26 -> 104.58905
A27: 24 | B27: ST20 | C27: Side(1m x 2.0m) | D27: 200 | E27: 1000 | F27: 2000 | G27: 70 | H27: 70 | I27: 29 | J27: =I27*$J$2 -> 145 | K27: =1.15*2.15*180 -> 445.05 | L27: =K27*$L$2*2 -> 4.945 | M27: =J27+L27 -> 149.945 | N27: 300 | O27: =N27+100 -> 400 | P27: 1200 TON | Q27: ='Equipment Costs(Press_Machine)'!$F$43 -> 34.596964 | R27: =3600/O27 -> 9 | S27: =Q27/R27 -> 3.8441071 | T27: 2 | U27: =LABOUR_Cost!$B$17 -> 7.2154472 | V27: =T27*U27/R27 -> 1.6034327 | W27: =S27+V27 -> 5.4475398 | X27: ='Equipment Costs(Drilling)'!$F$39 -> 7.8894021 | Y27: 30 | Z27: =X27/Y27 -> 0.26298007 | AA27: 2 | AB27: =LABOUR_Cost!$B$17 -> 7.2154472 | AC27: =AA27*AB27/Y27 -> 0.48102981 | AD27: =Z27+AC27 -> 0.74400988 | AE27: =M27+W27+AD27 -> 156.13655

Sheet LABOUR_Cost
A1: Direct labor cost | F1: CONFIDENTIAL
A2: * Working time
B3: Hr/Day | C3: Normial Working days/ Month | D3: Working time
A4: Regular Time(Week days) | B4: 8 | C4: 20 days | D4: 160
A5: Regular Time(Saturday) | B5: 4 | C5: 4 days | D5: 16
A6: Overtime Time | D6: 70
A7: 계 | D7: =SUM(D4:D6) -> 246
A9: * Wage rate
B10: Cost/year | C10: Cost/Mon | D10: Rate / Hr * Person | E10: Remark
A11: Direct labor cost | B11: 12000 | C11: =B11/12 -> 1000 | D11: =C11/$D$7 -> 4.0650407
A12: Paid leave cost (Monthly, Annual leave) | B12: =1000 -> 1000 | C12: =B12/12 -> 83.333333 | D12: =C12/$D$7 -> 0.33875339
A13: other employee benefits | B13: =1200000/1000 -> 1200 | C13: =B13/12 -> 100 | D13: =C13/$D$7 -> 0.40650407
A14: indirect labor cost | B14: =B34/2 -> 7100 | C14: =B14/12 -> 591.66667 | D14: =C14/$D$7 -> 2.4051491 | E14: 1/2 Person
C15: =SUM(C11:C14) -> 1775 | D15: =SUM(D11:D14) -> 7.2154472
A17: Direct Labor rate | B17: =D15 -> 7.2154472 | C17: /HR
A21: Indirect labor cost
A22: * Working time
B23: Hr/Day | C23: Normial Working days/ Month | D23: Working time
A24: Regular Time(Week days) | B24: 8 | C24: 20 days | D24: 160
A25: Regular Time(Saturday) | B25: 4 | C25: 4 days | D25: 16
A26: Overtime Time | D26: 70
A27: TOTAL | D27: =SUM(D24:D26) -> 246
A29: * Wage rate
B30: Cost/year | C30: Cost/Mon | D30: Rate / Hr * Person | E30: 비고
A31: Direct labor cost | B31: =1000*12*1 -> 12000 | C31: =B31/12 -> 1000 | D31: =C31/$D$27 -> 4.0650407 | E31: 1 persons
A32: Paid leave cost (Monthly, Annual leave) | B32: =1000 -> 1000 | C32: =B32/12 -> 83.333333 | D32: =C32/$D$27 -> 0.33875339
A33: other employee benefits | B33: =1200000/1000 -> 1200 | C33: =B33/12 -> 100 | D33: =C33/$D$27 -> 0.40650407
B34: =SUM(B31:B33) -> 14200 | C34: =SUM(C31:C33) -> 1183.3333 | D34: =SUM(D31:D33) -> 4.8102981
A36: Direct Labor rate | B36: =D15 -> 7.2154472 | C36: /Hr
A37: Indirect Labor rate | B37: =D34 -> 4.8102981 | C37: /Hr

Sheet Equipment Costs(Press_Machine)
A1: PRESS MACHINE(FIXED EXPENSE/MONTH)
I2: 44377
A3: Press machine | C3: Buying Price | D3: 1. Depreciation | E3: 2. Other Depreciation (Buliding,auxiliary machinaries and tools) | F3: 3.repair & maintenance | G3: 4.Eletricity cost(Fixed) | H3: 5. Other expense | I3: Total
D4: 5 year | F4: Depreciation*20%
A5: 1500 TON | C5: 300000 | D5: =C5/5/12 -> 5000 | E5: 2000 | F5: =D5*0.2 -> 1000 | G5: =C10 -> 1400 | H5: 2000 | I5: =SUM(D5:H5) -> 11400
A7: 1. Electricity cost (Fixed Basic fare)
A8: Contracted Power consumption | C8: 200 | D8: KW
A9: US$/ KWH | C9: 7
A10: Electricity cost (Fixed Basic fare) | C10: =C9*C8 -> 1400
A12: PRESS MACHINE(VARIABLE EXPENSE/MONTH)
A13: 1. Press Production time
A14: Press machine | C14: Production time/ DAY | D14: Working Days/Month | E14: Production time/ Month
A15: 1200 TON | B15: WORKING TIME (Week days) | C15: 20 | D15: 20 | E15: =C15*D15 -> 400
B16: WORKING TIME (Saturday) | C16: 8 | D16: 4 | E16: =C16*D16 -> 32
A17: 800 TON | B17: WORKING TIME (Week days) | C17: 20 | D17: 20 | E17: =C17*D17 -> 400
B18: WORKING TIME (Saturday) | C18: 8 | D18: 4 | E18: =C18*D18 -> 32
A19: 800 TON | B19: WORKING TIME (Week days) | C19: 20 | D19: 20 | E19: =C19*D19 -> 400
B20: WORKING TIME (Saturday) | C20: 8 | D20: 4 | E20: =C20*D20 -> 32
A21: TOTAL | C21: =SUM(C15:C20) -> 84 | D21: =SUM(D15:D20) -> 72 | E21: =SUM(E15:E20) -> 1296
A23: 2. Variable Expense
C24: Expense / Month | D24: Expense /HR
A25: 1. Consumables cost (Cutter, Ink and etc) | C25: 500 | D25: =C25/$E$21 -> 0.38580247
A26: 2. Electricity cost(Variable expense) | C26: =150*0.1 -> 15 | D26: =C26/$E$21 -> 0.011574074 | E26: KWD 0.1/KW
A27: 3.Others(waste contribution, etc) | C27: 1000 | D27: =C27/$E$21 -> 0.77160494
A28: Total | C28: =SUM(C25:C27) -> 1515 | D28: =SUM(D25:D27) -> 1.1689815
A30: 3. PRESS MACHINE(VARIABLE EXPENSE/HR)
A31: Press machine | C31: Consumables cost | D31: Electricity cost (Variable expense) | E31: Others(waste contribution, etc) | F31: Total/HR
A32: 1200ton, 800ton, 800ton | C32: =D25 -> 0.38580247 | D32: =D26 -> 0.011574074 | E32: =D27 -> 0.77160494 | F32: =SUM(C32:E32) -> 1.1689815
A35: 3. PRESS MACHINE(TOTAL EXPENSE/MONTH)
A37: Time available / Days | C37: 20.6 | D37: Hours | E37: Planned Time available /Month | F37: =C37*C38*C39/C40 -> 401.01333
A38: Working days / Year | C38: 292 | D38: Days
A39: Planned availability | C39: 0.8 | D39: %
A40: Months/year | C40: 12 | D40: Month
A42: MACHINE | B42: Fixed expense/Month | C42: Variable expense/HR | D42: Boiler Expense/HR | E42: Fixed expense/HR | F42: Total expense/HR
A43: 1500 TON | B43: =I5 -> 11400 | C43: =F32 -> 1.1689815 | D43: =50*0.1 -> 5 | E43: =B43/F37 -> 28.427982 | F43: =C43+D43+E43 -> 34.596964

Sheet Equipment Costs(Drilling)
A1: Drilling Machine(FIXED EXPENSE/MONTH)
I2: 44377
A3: Machinary | C3: Buying Price | D3: 1. Depreciation | E3: 2. Other Depreciation (Buliding,auxiliary machinaries and tools) | F3: 3.repair & maintenance | G3: 4.Eletricity cost(Fixed) | H3: 5. Other expense | I3: Total
D4: 5 year | F4: Depreciation*20%
A5: Drilling Machine(FIXED EXPENSE/MONTH) | C5: 100000 | D5: =C5/5/12 -> 1666.6667 | E5: 500 | F5: =D5*0.2 -> 333.33333 | G5: =C10 -> 70 | H5: 500 | I5: =SUM(D5:H5) -> 3070
A7: 1. Electricity cost (Fixed Basic fare)
A8: Contracted Power consumption | C8: 10 | D8: KW
A9: US$/ KWH | C9: 7
A10: Electricity cost (Fixed Basic fare) | C10: =C9*C8 -> 70
A12: Drilling Machine(VARIABLE EXPENSE/MONTH)
A14: Press machine | C14: Production time/ DAY | D14: Working Days/Month | E14: Production time/ Month
A15: Drilling Machine | B15: WORKING TIME (Week days) | C15: 20 | D15: 20 | E15: =C15*D15 -> 400
B16: WORKING TIME (Saturday) | C16: 8 | D16: 4 | E16: =C16*D16 -> 32
A17: TOTAL | C17: =SUM(C15:C16) -> 28 | D17: =SUM(D15:D16) -> 24 | E17: =SUM(E15:E16) -> 432
A19: 2. Variable Expense
C20: Expense / Month | D20: Expense /HR
A21: 1. Consumables cost (Cutter, Ink and etc) | D21: =C21/$E$17 -> 0
A22: 2. Electricity cost(Variable expense) | C22: =10*0.1 -> 1 | D22: =C22/$E$17 -> 0.0023148148 | E22: USD 0.1/KW
A23: 3.Others(waste contribution, etc) | C23: 100 | D23: =C23/$E$17 -> 0.23148148
A24: Total | C24: =SUM(C21:C23) -> 101 | D24: =SUM(D21:D23) -> 0.2337963
A26: 3. Drilling Machine(VARIABLE EXPENSE/HR)
A27: Press machine | C27: Consumables cost | D27: Electricity cost (Variable expense) | E27: Others(waste contribution, etc) | F27: Total/HR
A28: Drilling Machine | C28: =D21 -> 0 | D28: =D22 -> 0.0023148148 | E28: =D23 -> 0.23148148 | F28: =SUM(C28:E28) -> 0.2337963
A31: 3. PRESS MACHINE(TOTAL EXPENSE/MONTH)
A33: Time available / Days | C33: 20.6 | D33: Hours | E33: Planned Time available /Month | F33: =C33*C34*C35/C36 -> 401.01333
A34: Working days / Year | C34: 292 | D34: Days
A35: Planned availability | C35: 0.8 | D35: %
A36: Months/year | C36: 12 | D36: Month
A38: MACHINE | B38: Fixed expense/Month | C38: Variable expense/HR | D38: Boiler Expense/HR | E38: Fixed expense/HR | F38: Total expense/HR
A39: Drilling Machine | B39: =I5 -> 3070 | C39: =F28 -> 0.2337963 | E39: =B39/F33 -> 7.6556058 | F39: =C39+D39+E39 -> 7.8894021

Sheet Sheet1
